nooz/__init__.py
nooz/boxes.py
nooz/helper.py
nooz/model.py
nooz/run.py
nooz/views.py
nooz/widgets.py
nooz-0.1.0.dist-info/LICENSE
nooz-0.1.0.dist-info/METADATA
nooz-0.1.0.dist-info/WHEEL
nooz-0.1.0.dist-info/entry_points.txt
nooz-0.1.0.dist-info/top_level.txt
nooz-0.1.0.dist-info/zip-safe
nooz-0.1.0.dist-info/RECORD
