Metadata-Version: 2.1
Name: nooz
Version: 0.1.0
Summary: Trending headlines right in your terminal.
Home-page: https://github.com/preetmishra/nooz
Author: Preet Mishra
Author-email: ipreetmishra@gmail.com
License: MIT
Keywords: news
Platform: UNKNOWN
Classifier: Development Status :: 3 - Alpha
Classifier: Intended Audience :: End Users/Desktop
Classifier: Topic :: Internet
Classifier: License :: OSI Approved :: MIT License
Classifier: Programming Language :: Python :: 3
Classifier: Programming Language :: Python :: 3.5
Classifier: Programming Language :: Python :: 3.6
Classifier: Programming Language :: Python :: 3.7
Classifier: Programming Language :: Python :: 3.8
Classifier: Operating System :: OS Independent
Requires-Python: >=3.5, <=3.8
Requires-Dist: mypy-extensions (>=0.4)
Requires-Dist: requests (>=2.23.0)
Requires-Dist: urwid (==2.1.0)
Requires-Dist: urllib3 (>=1.25.8)
Provides-Extra: linting
Requires-Dist: mypy (==0.761) ; extra == 'linting'
Requires-Dist: pycodestyle (==2.5.0) ; extra == 'linting'
